[
  {
    "title": "test1",
    "name": "testname1",
    "description": "testdesc1",
    "participants": [
      "testname1",
      "testname2"
    ],
    "expenses": [
      {
        "name": "testwhat1",
        "contributor": "testname1",
        "amount": 10,
        "beneficiaries": [
          "testname1",
          "testname2"
        ],
        "id": 1
      },
      {
        "name": "testwhat2",
        "contributor": "testname2",
        "amount": 20,
        "beneficiaries": [
          "testname1",
          "testname2"
        ],
        "id": 2
      }
    ],
    "id": 1
  },
  {
    "title": "test2",
    "name": "testname2",
    "description": "testdesc2",
    "participants": [
      "testname2"
    ],
    "expenses": [
      {
        "name": "dinner",
        "contributor": "testname2",
        "amount": "20",
        "beneficiaries": [
          "testname2",
          "testname3"
        ],
        "id": 1
      },
      {
        "name": "breakfast",
        "contributor": "testname2",
        "amount": "27",
        "beneficiaries": [
          "testname2",
          "testname4"
        ],
        "id": 2
      }
    ],
    "id": 2
  }
]